geocode_lite/__about__.py
geocode_lite/__init__.py
geocode_lite/__main__.py
geocode_lite/api_key_manager.py
geocode_lite/geocoder.py
geocode_lite-0.5.6.dist-info/DESCRIPTION.rst
geocode_lite-0.5.6.dist-info/METADATA
geocode_lite-0.5.6.dist-info/RECORD
geocode_lite-0.5.6.dist-info/WHEEL
geocode_lite-0.5.6.dist-info/metadata.json
geocode_lite-0.5.6.dist-info/top_level.txt
