Metadata-Version: 2.0
Name: geocode-lite
Version: 0.5.6
Summary: Basic python tool to get lat/long of address using Google Map API
Home-page: https://github.com/clgx/api-key-manager-python
Author: Camille Daum-Lobko
Author-email: camille@daum-lobko.com
License: Apache License, Version 2.0
Platform: UNKNOWN
Classifier: Development Status :: 4 - Beta
Classifier: Intended Audience :: Developers
Classifier: License :: OSI Approved :: Apache Software License
Classifier: Programming Language :: Python :: 3
Classifier: Programming Language :: Python :: 3.2
Classifier: Programming Language :: Python :: 3.3
Classifier: Programming Language :: Python :: 3.4
Classifier: Programming Language :: Python :: 3.5
Classifier: Programming Language :: Python :: 3.6
Requires-Python: >=3
Requires-Dist: cryptography (>=1.9)
Requires-Dist: googlemaps (>=2.5.1)
